micropython_bmi270/__init__.py
micropython_bmi270/bmi270.py
micropython_bmi270/config_file.py
micropython_bmi270/i2c_helpers.py
micropython_bmi270-0.1.0.dist-info/LICENSE
micropython_bmi270-0.1.0.dist-info/METADATA
micropython_bmi270-0.1.0.dist-info/WHEEL
micropython_bmi270-0.1.0.dist-info/top_level.txt
micropython_bmi270-0.1.0.dist-info/RECORD
