Metadata-Version: 2.1
Name: micropython-bmi270
Version: 0.1.0
Summary: MicroPython Driver for the Bosch BMI270 Accelerometer/Gyro Sensor
Author-email: JDM <xxyx@mailmeto.mozmail.com>
License: MIT
Project-URL: Homepage, https://github.com/jposada202020/MicroPython_BMI270
Keywords: sensor,micropython,bmi270,micropython,driver,sensor,bosch,bmi270,acceleration,accelerometer,gyro
Classifier: Intended Audience :: Developers
Classifier: Topic :: Software Development :: Libraries
Classifier: Topic :: Software Development :: Embedded Systems
Classifier: Topic :: System :: Hardware
Classifier: License :: OSI Approved :: MIT License
Classifier: Programming Language :: Python :: Implementation :: MicroPython
License-File: LICENSE
